LICENSE.txt
MANIFEST.in
README.rst
setup.py
docs/Makefile
docs/source/conf.py
docs/source/index.rst
docs/source/screenshots.rst
docs/source/static/1_in_menu.png
docs/source/static/2_index.png
docs/source/static/3_create_edit.png
docs/source/static/4_create_edit_condensed.png
docs/source/static/5_index_rule.png
robots/__init__.py
robots/models.py
robots/panels.py
robots/settings.py
robots/urls.py
robots/views.py
robots/wagtail_hooks.py
robots/migrations/0001_initial.py
robots/migrations/__init__.py
robots/templates/robots/rule_list.html
robots/test/__init__.py
robots/test/apps.py
robots/test/settings.py
robots/test/urls.py
robots/test/tests/__init__.py
robots/test/tests/test_e2e.py
wagtail_robots.egg-info/PKG-INFO
wagtail_robots.egg-info/SOURCES.txt
wagtail_robots.egg-info/dependency_links.txt
wagtail_robots.egg-info/requires.txt
wagtail_robots.egg-info/top_level.txt